{
    "director_name": "Charles Burnett",
    "imdb_uri": "https://www.imdb.com/name/nm0122344/fullcredits/",
    "credits": [
        {
            "title": "Untitled Policing Documentary",
            "uri": "https://www.imdb.com/title/tt16042972/?ref_=nm_flmg_dr_1",
            "year": "",
            "note": "(Documentary) (filming)"
        },
        {
            "title": "After the LockDown: Black in LA",
            "uri": "https://www.imdb.com/title/tt13503300/?ref_=nm_flmg_dr_2",
            "year": "2021",
            "note": "(Documentary)"
        },
        {
            "title": "Cinetracts '20",
            "uri": "https://www.imdb.com/title/tt13472328/?ref_=nm_flmg_dr_3",
            "year": "2020",
            "note": "(Documentary short)"
        },
        {
            "title": "Power to Heal: Medicare and the Civil Rights Revolution",
            "uri": "https://www.imdb.com/title/tt8359476/?ref_=nm_flmg_dr_4",
            "year": "2018",
            "note": "(TV Movie documentary)"
        },
        {
            "title": "Juliette Fairley's Mulatto's Dilemma",
            "uri": "https://www.imdb.com/title/tt2146170/?ref_=nm_flmg_dr_5",
            "year": "2012",
            "note": "(Short)"
        },
        {
            "title": "Mulatto Saga",
            "uri": "https://www.imdb.com/title/tt2245013/?ref_=nm_flmg_dr_6",
            "year": "2012",
            "note": "(Short)"
        },
        {
            "title": "42 One Dream Rush",
            "uri": "https://www.imdb.com/title/tt2073510/?ref_=nm_flmg_dr_7",
            "year": "2010",
            "note": "(Short)"
        },
        {
            "title": "Relative Stranger",
            "uri": "https://www.imdb.com/title/tt1252330/?ref_=nm_flmg_dr_8",
            "year": "2009",
            "note": "(TV Movie)"
        },
        {
            "title": "Quiet as Kept",
            "uri": "https://www.imdb.com/title/tt1459232/?ref_=nm_flmg_dr_9",
            "year": "2007",
            "note": "(Short)"
        },
        {
            "title": "Namibia: The Struggle for Liberation",
            "uri": "https://www.imdb.com/title/tt1085469/?ref_=nm_flmg_dr_10",
            "year": "2007",
            "note": ""
        },
        {
            "title": "Independent Lens",
            "uri": "https://www.imdb.com/title/tt0486531/?ref_=nm_flmg_dr_11",
            "year": "2004",
            "note": "(TV Series documentary) (1 episode) - Nat Turner: A Troublesome Property ()"
        },
        {
            "title": "The Blues",
            "uri": "https://www.imdb.com/title/tt0287198/?ref_=nm_flmg_dr_12",
            "year": "2003",
            "note": "(TV Mini Series documentary) (1 episode) - Warming by the Devil's Fire ()"
        },
        {
            "title": "For Reel?",
            "uri": "https://www.imdb.com/title/tt0339018/?ref_=nm_flmg_dr_13",
            "year": "2003",
            "note": "(TV Movie documentary)"
        },
        {
            "title": "Nat Turner: A Troublesome Property",
            "uri": "https://www.imdb.com/title/tt0354763/?ref_=nm_flmg_dr_14",
            "year": "2003",
            "note": "(Documentary)"
        },
        {
            "title": "American Family",
            "uri": "https://www.imdb.com/title/tt0303635/?ref_=nm_flmg_dr_15",
            "year": "2002",
            "note": "(TV Series)"
        },
        {
            "title": "Finding Buck McHenry",
            "uri": "https://www.imdb.com/title/tt0244512/?ref_=nm_flmg_dr_16",
            "year": "2000",
            "note": "(TV Movie)"
        },
        {
            "title": "Olivia's Story",
            "uri": "https://www.imdb.com/title/tt0234375/?ref_=nm_flmg_dr_17",
            "year": "2000",
            "note": "(Short)"
        },
        {
            "title": "The Annihilation of Fish",
            "uri": "https://www.imdb.com/title/tt0212772/?ref_=nm_flmg_dr_18",
            "year": "1999",
            "note": ""
        },
        {
            "title": "The Wonderful World of Disney",
            "uri": "https://www.imdb.com/title/tt0132666/?ref_=nm_flmg_dr_19",
            "year": "1999",
            "note": "(TV Series) (1 episode) - Selma, Lord, Selma ()"
        },
        {
            "title": "Dr. Endesha Ida Mae Holland",
            "uri": "https://www.imdb.com/title/tt0168711/?ref_=nm_flmg_dr_20",
            "year": "1998",
            "note": "(Documentary short)"
        },
        {
            "title": "The Wedding",
            "uri": "https://www.imdb.com/title/tt0143076/?ref_=nm_flmg_dr_21",
            "year": "1998",
            "note": "(TV Movie)"
        },
        {
            "title": "The Final Insult",
            "uri": "https://www.imdb.com/title/tt11006022/?ref_=nm_flmg_dr_22",
            "year": "1997",
            "note": "(Documentary)"
        },
        {
            "title": "Documenta X - Die Filme",
            "uri": "https://www.imdb.com/title/tt0125723/?ref_=nm_flmg_dr_23",
            "year": "1997",
            "note": "(Documentary)"
        },
        {
            "title": "Nightjohn",
            "uri": "https://www.imdb.com/title/tt0117180/?ref_=nm_flmg_dr_24",
            "year": "1996",
            "note": "(TV Movie)"
        },
        {
            "title": "When It Rains",
            "uri": "https://www.imdb.com/title/tt0114915/?ref_=nm_flmg_dr_25",
            "year": "1995",
            "note": "(Short)"
        },
        {
            "title": "The Glass Shield",
            "uri": "https://www.imdb.com/title/tt0109906/?ref_=nm_flmg_dr_26",
            "year": "1994",
            "note": ""
        },
        {
            "title": "America Becoming",
            "uri": "https://www.imdb.com/title/tt0254954/?ref_=nm_flmg_dr_27",
            "year": "1991",
            "note": "(Documentary)"
        },
        {
            "title": "To Sleep with Anger",
            "uri": "https://www.imdb.com/title/tt0100791/?ref_=nm_flmg_dr_28",
            "year": "1990",
            "note": ""
        },
        {
            "title": "My Brother's Wedding",
            "uri": "https://www.imdb.com/title/tt0087763/?ref_=nm_flmg_dr_29",
            "year": "1983",
            "note": ""
        },
        {
            "title": "Killer of Sheep",
            "uri": "https://www.imdb.com/title/tt0076263/?ref_=nm_flmg_dr_30",
            "year": "1978",
            "note": ""
        },
        {
            "title": "The Horse",
            "uri": "https://www.imdb.com/title/tt0206022/?ref_=nm_flmg_dr_31",
            "year": "1973",
            "note": "(Short)"
        },
        {
            "title": "Several Friends",
            "uri": "https://www.imdb.com/title/tt0206284/?ref_=nm_flmg_dr_32",
            "year": "1969",
            "note": "(Short)"
        }
    ]
}
