{
    "director_name": "Lynn Shelton",
    "imdb_uri": "https://www.imdb.com/name/nm1119645/fullcredits/",
    "credits": [
        {
            "title": "Madame X",
            "uri": "https://www.imdb.com/title/tt4507174/?ref_=nm_flmg_dr_1",
            "year": "",
            "note": "(TV Mini Series) (1 episode) (announced) - Episode #1.2"
        },
        {
            "title": "Little Fires Everywhere",
            "uri": "https://www.imdb.com/title/tt8089592/?ref_=nm_flmg_dr_2",
            "year": "2020",
            "note": "(TV Mini Series) (4 episodes) - Find a Way () - Duo () - The Spider Web () - The Spark ()"
        },
        {
            "title": "Marc Maron: End Times Fun",
            "uri": "https://www.imdb.com/title/tt11810418/?ref_=nm_flmg_dr_3",
            "year": "2020",
            "note": "(TV Special)"
        },
        {
            "title": "The Morning Show",
            "uri": "https://www.imdb.com/title/tt7203552/?ref_=nm_flmg_dr_4",
            "year": "2019",
            "note": "(TV Series) (1 episode) - That Woman ()"
        },
        {
            "title": "Dickinson",
            "uri": "https://www.imdb.com/title/tt8518136/?ref_=nm_flmg_dr_5",
            "year": "2019",
            "note": "(TV Series) (2 episodes) - Alone, I Cannot Be () - Wild Nights ()"
        },
        {
            "title": "GLOW",
            "uri": "https://www.imdb.com/title/tt5770786/?ref_=nm_flmg_dr_6",
            "year": "2017-2019",
            "note": "(TV Series) (5 episodes) - A Very Christmas (2019) - Keep Ridin' (2019) - Work the Leg (2018) - Viking Funeral (2018) - The Liberal Chokehold (2017)"
        },
        {
            "title": "A.P. Bio",
            "uri": "https://www.imdb.com/title/tt6461726/?ref_=nm_flmg_dr_7",
            "year": "2018-2019",
            "note": "(TV Series) (2 episodes) - Nuns (2019) - Drenching Dallas (2018) ... (directed by)"
        },
        {
            "title": "Sword of Trust",
            "uri": "https://www.imdb.com/title/tt8484012/?ref_=nm_flmg_dr_8",
            "year": "2019",
            "note": ""
        },
        {
            "title": "Love",
            "uri": "https://www.imdb.com/title/tt4061080/?ref_=nm_flmg_dr_9",
            "year": "2017-2018",
            "note": "(TV Series) (4 episodes) - Catalina (2018) - You're My Gran Torino (2018) - Marty Dobbs (2017) - A Day (2017)"
        },
        {
            "title": "Fresh Off the Boat",
            "uri": "https://www.imdb.com/title/tt3551096/?ref_=nm_flmg_dr_10",
            "year": "2015-2017",
            "note": "(TV Series) (9 episodes) - Four Funerals and a Wedding (2017) - Louisween (2016) - Tight Two (2016) - The Big 1-2 (2015) - Shaquille O'Neal Motors (2015) - Family Business Trip (2015) - Showdown at the Golden Saddle (2015) - Persistent Romeo (2015) - Pilot (2015)"
        },
        {
            "title": "Ghosted",
            "uri": "https://www.imdb.com/title/tt6053538/?ref_=nm_flmg_dr_11",
            "year": "2017",
            "note": "(TV Series) (1 episode) - Bee-Mo ()"
        },
        {
            "title": "Outside In",
            "uri": "https://www.imdb.com/title/tt7260048/?ref_=nm_flmg_dr_12",
            "year": "2017",
            "note": ""
        },
        {
            "title": "Marc Maron: Too Real",
            "uri": "https://www.imdb.com/title/tt7335938/?ref_=nm_flmg_dr_13",
            "year": "2017",
            "note": "(TV Special)"
        },
        {
            "title": "Casual",
            "uri": "https://www.imdb.com/title/tt4577466/?ref_=nm_flmg_dr_14",
            "year": "2016-2017",
            "note": "(TV Series) (3 episodes) - Ashes to Ashes (2017) - The Magpie (2016) - Threesomes (2016)"
        },
        {
            "title": "Santa Clarita Diet",
            "uri": "https://www.imdb.com/title/tt5580540/?ref_=nm_flmg_dr_15",
            "year": "2017",
            "note": "(TV Series) (1 episode) - Strange or Just Inconsiderate? ()"
        },
        {
            "title": "The Good Place",
            "uri": "https://www.imdb.com/title/tt4955642/?ref_=nm_flmg_dr_16",
            "year": "2017",
            "note": "(TV Series) (1 episode) - What's My Motivation ()"
        },
        {
            "title": "Maron",
            "uri": "https://www.imdb.com/title/tt2520512/?ref_=nm_flmg_dr_17",
            "year": "2016",
            "note": "(TV Series) (2 episodes) - Marc's Roommate () - Step 1 ()"
        },
        {
            "title": "Shameless",
            "uri": "https://www.imdb.com/title/tt1586680/?ref_=nm_flmg_dr_18",
            "year": "2016",
            "note": "(TV Series) (1 episode) - Paradise Lost () ... (directed by)"
        },
        {
            "title": "Master of None",
            "uri": "https://www.imdb.com/title/tt4635276/?ref_=nm_flmg_dr_19",
            "year": "2015",
            "note": "(TV Series) (2 episodes) - Ladies and Gentlemen () - Old People ()"
        },
        {
            "title": "The Mindy Project",
            "uri": "https://www.imdb.com/title/tt2211129/?ref_=nm_flmg_dr_20",
            "year": "2014-2015",
            "note": "(TV Series) (2 episodes) - Danny Castellano Is My Nutritionist (2015) - I Slipped (2014)"
        },
        {
            "title": "New Girl",
            "uri": "https://www.imdb.com/title/tt1826940/?ref_=nm_flmg_dr_21",
            "year": "2012-2014",
            "note": "(TV Series) (5 episodes) - Dice (2014) - Mars Landing (2014) - First Date (2013) - Pepperwood (2013) - Injured (2012)"
        },
        {
            "title": "Laggies",
            "uri": "https://www.imdb.com/title/tt2034031/?ref_=nm_flmg_dr_22",
            "year": "2014",
            "note": ""
        },
        {
            "title": "Touchy Feely",
            "uri": "https://www.imdb.com/title/tt2364949/?ref_=nm_flmg_dr_23",
            "year": "2013",
            "note": ""
        },
        {
            "title": "Ben and Kate",
            "uri": "https://www.imdb.com/title/tt2177491/?ref_=nm_flmg_dr_24",
            "year": "2012",
            "note": "(TV Series) (1 episode) - The Trip ()"
        },
        {
            "title": "Your Sister's Sister",
            "uri": "https://www.imdb.com/title/tt1742336/?ref_=nm_flmg_dr_25",
            "year": "2011",
            "note": ""
        },
        {
            "title": "Mad Men",
            "uri": "https://www.imdb.com/title/tt0804503/?ref_=nm_flmg_dr_26",
            "year": "2010",
            "note": "(TV Series) (1 episode) - Hands and Knees ()"
        },
        {
            "title": "$5 Cover: Seattle",
            "uri": "https://www.imdb.com/title/tt1500291/?ref_=nm_flmg_dr_27",
            "year": "2009",
            "note": "(TV Series)"
        },
        {
            "title": "Humpday",
            "uri": "https://www.imdb.com/title/tt1334537/?ref_=nm_flmg_dr_28",
            "year": "2009",
            "note": ""
        },
        {
            "title": "My Effortless Brilliance",
            "uri": "https://www.imdb.com/title/tt1183684/?ref_=nm_flmg_dr_29",
            "year": "2008",
            "note": ""
        },
        {
            "title": "What the Funny",
            "uri": "https://www.imdb.com/title/tt1323557/?ref_=nm_flmg_dr_30",
            "year": "2008",
            "note": "(Video)"
        },
        {
            "title": "We Go Way Back",
            "uri": "https://www.imdb.com/title/tt0468580/?ref_=nm_flmg_dr_31",
            "year": "2006",
            "note": ""
        }
    ]
}
